flask_s3.py
Flask_S3_gzip-0.1.6.dist-info/DESCRIPTION.rst
Flask_S3_gzip-0.1.6.dist-info/METADATA
Flask_S3_gzip-0.1.6.dist-info/metadata.json
Flask_S3_gzip-0.1.6.dist-info/RECORD
Flask_S3_gzip-0.1.6.dist-info/top_level.txt
Flask_S3_gzip-0.1.6.dist-info/WHEEL
