Metadata-Version: 2.0
Name: Flask-S3-gzip
Version: 0.1.6
Summary: Seamlessly serve the static files of your Flask app from Amazon S3 (forked from original flask-s3)
Home-page: http://github.com/spoqa/flask-s3
Author: Spoqa
Author-email: dev@spoqa.com
License: MIT License
Platform: any
Classifier: Environment :: Web Environment
Classifier: Intended Audience :: Developers
Classifier: License :: Other/Proprietary License
Classifier: Operating System :: OS Independent
Classifier: Programming Language :: Python
Classifier: Topic :: Internet :: WWW/HTTP :: Dynamic Content
Classifier: Topic :: Software Development :: Libraries :: Python Modules
Requires-Dist: Flask
Requires-Dist: Boto (>=2.5.2)
Requires-Dist: futures
